{
  "main": {
    "id": "6936d29bcde0e4ce",
    "type": "split",
    "children": [
      {
        "id": "6fa508458dd4128c",
        "type": "tabs",
        "children": [
          {
            "id": "41f62539f23cc408",
            "type": "leaf",
            "state": {
              "type": "markdown",
              "state": {
                "file": "CCICOMP/Number Systems.md",
                "mode": "preview",
                "source": false
              },
              "icon": "lucide-file",
              "title": "Number Systems"
            }
          }
        ]
      }
    ],
    "direction": "vertical"
  },
  "left": {
    "id": "f00794f5aab1ef26",
    "type": "split",
    "children": [
      {
        "id": "92483214e3c310b7",
        "type": "tabs",
        "children": [
          {
            "id": "353e06f3cef629e2",
            "type": "leaf",
            "state": {
              "type": "file-explorer",
              "state": {
                "sortOrder": "alphabetical",
                "autoReveal": false
              },
              "icon": "lucide-folder-closed",
              "title": "Files"
            }
          },
          {
            "id": "6d1713b28d51a987",
            "type": "leaf",
            "state": {
              "type": "search",
              "state": {
                "query": "",
                "matchingCase": false,
                "explainSearch": false,
                "collapseAll": false,
                "extraContext": false,
                "sortOrder": "alphabetical"
              },
              "icon": "lucide-search",
              "title": "Search"
            }
          },
          {
            "id": "fcc2bf57274170a8",
            "type": "leaf",
            "state": {
              "type": "bookmarks",
              "state": {},
              "icon": "lucide-bookmark",
              "title": "Bookmarks"
            }
          }
        ]
      }
    ],
    "direction": "horizontal",
    "width": 300
  },
  "right": {
    "id": "0eceac8c1892e993",
    "type": "split",
    "children": [
      {
        "id": "908e07b64b26c258",
        "type": "tabs",
        "children": [
          {
            "id": "5ccc63bd25aa80c8",
            "type": "leaf",
            "state": {
              "type": "backlink",
              "state": {
                "file": "CCICOMP/Number Systems.md",
                "collapseAll": false,
                "extraContext": false,
                "sortOrder": "alphabetical",
                "showSearch": false,
                "searchQuery": "",
                "backlinkCollapsed": false,
                "unlinkedCollapsed": true
              },
              "icon": "links-coming-in",
              "title": "Backlinks for Number Systems"
            }
          },
          {
            "id": "51e0e90f6564bee3",
            "type": "leaf",
            "state": {
              "type": "outgoing-link",
              "state": {
                "file": "CCICOMP/Number Systems.md",
                "linksCollapsed": false,
                "unlinkedCollapsed": true
              },
              "icon": "links-going-out",
              "title": "Outgoing links from Number Systems"
            }
          },
          {
            "id": "3b3244418997567d",
            "type": "leaf",
            "state": {
              "type": "tag",
              "state": {
                "sortOrder": "frequency",
                "useHierarchy": true,
                "showSearch": false,
                "searchQuery": ""
              },
              "icon": "lucide-tags",
              "title": "Tags"
            }
          },
          {
            "id": "48582ae8db5ee711",
            "type": "leaf",
            "state": {
              "type": "outline",
              "state": {
                "file": "CCICOMP/Number Systems.md",
                "followCursor": false,
                "showSearch": false,
                "searchQuery": ""
              },
              "icon": "lucide-list",
              "title": "Outline of Number Systems"
            }
          }
        ]
      }
    ],
    "direction": "horizontal",
    "width": 300,
    "collapsed": true
  },
  "left-ribbon": {
    "hiddenItems": {
      "switcher:Open quick switcher": false,
      "graph:Open graph view": false,
      "canvas:Create new canvas": false,
      "daily-notes:Open today's daily note": false,
      "templates:Insert template": false,
      "command-palette:Open command palette": false,
      "obsidian-git:Open Git source control": false
    }
  },
  "active": "353e06f3cef629e2",
  "lastOpenFiles": [
    "Untitled.md",
    "CCICOMP/Number Systems.md",
    "Testing.md",
    "Welcome.md",
    "CCICOMP"
  ]
}